Workbook

Sheet Main
B2: CHAPEL DOWN GROUP PLC | J2: * all numbers in thousands
B3: LON: CDGP
B4: Founded: 2002 | J4: Capital Structure
B5: IPO: Dec 2023 | J5: Price | K5: 0.35 | L5: 35.00 GBX
B6: Employees: 92 | J6: Shares | K6: =171520 -> 171520
J7: MC | K7: =K5*K6 -> 60032
B8: Sector: Consumer Defensive | J8: Debt | K8: =9225+9975+376 -> 19576 | L8: FY2024
B9: Core operations: Production and sale of alcoholic beverages in the UK and internationally | J9: Cash | K9: 981.963 | L9: FY2024
J10: EV | K10: =K7-K9+K8 -> 78626.037
B11: HQ: London | J11: Net debt | K11: =K8-K9 -> 18594.037
B12: England's leading winemaker, offering premium sparkling, white, and rosé wines
B13: It sells its products through its shops, as well as online | J13: EBIT | K13: 2452.958 | L13: FY2023
B14: Chapel Down is now the only English wine company with a stock market listing. | J14: EV/EBIT | K14: =K10/K13 -> 32.05356
J15: Earnings | K15: =Model!E20 -> 1527.353 | L15: FY2023
B16: *Our ambition is to win the equivalent of 1% of the 300 million bottle global Champagne market by 2035.
J17: Cash = Cash and cash equivalents
B18: Strategic report | J18: Debt = borrowings + current/non-current lease liabilities (interest-bearing debt)
B19: Sales | C19: 2024 | D19: 2023 | E19: Change, %
B20: Category
B21: Sparkling | C21: 10582 | D21: 11444 | E21: =(C21-D21)/D21 -> -0.075323314 | J21: Current assets | K21: =Model!F39 -> 31544.155 | L21: FY2024
B22: A Touch of Sparkle | C22: 1347 | D22: 1399 | E22: =(C22-D22)/D22 -> -0.037169407 | J22: Current liabilities | K22: =Model!F48 -> 15396.417 | L22: FY2024
B23: Still | C23: 3113 | D23: 2545 | E23: =(C23-D23)/D23 -> 0.22318271 | J23: Net working capital | K23: =K21-K22 -> 16147.738
B24: Spirits | C24: 161 | D24: 553 | E24: =(C24-D24)/D24 -> -0.70886076
B25: Tours & Other | C25: 1148 | D25: 1260 | E25: =(C25-D25)/D25 -> -0.088888889 | J25: Inventory intensity | K25: =Model!F37/Model!F43 -> 0.45502231 | L25: *normal as for production company
B26: Total | C26: =SUM(C21:C25) -> 16351 | D26: =SUM(D21:D25) -> 17201 | E26: =(C26-D26)/D26 -> -0.049415732 | J26: A/R intensity | K26: =Model!F38/Model!F43 -> 0.068610966 | L26: *healthy: little money is hanging in accounts receivable
B28: Channel | J28: Debt ratio | K28: =Model!F54/Model!F43 -> 0.44056821 | L28: *within healthy range: 44% of assets are financed by debt
B29: Off-trade | C29: 6790 | D29: 8428 | E29: =(C29-D29)/D29 -> -0.19435216 | J29: Debt-to-equity | K29: =Model!F54/Model!F56 -> 0.78752802 | L29: *market average (0.7637) - controlled risk
B30: On-trade | C30: 2460 | D30: 2122 | E30: =(C30-D30)/D30 -> 0.15928369 | J30: Equity ratio | K30: =Model!F56/Model!F43 -> 0.55943179 | L30: *low risk of bankruptcy
B31: International | C31: 684 | D31: 760 | E31: =(C31-D31)/D31 -> -0.1
B32: eCommerce | C32: 3755 | D32: 3070 | E32: =(C32-D32)/D32 -> 0.22312704 | J32: ROA | K32: =K15/AVERAGE(Model!C43:F43) -> 0.032652893 | L32: *very low level: every £100 of assets generates only £3 of profit
B33: Retail, Tours & Events | C33: 2241 | D33: 2250 | E33: =(C33-D33)/D33 -> -0.004 | J33: ROE | K33: =K15/AVERAGE(Model!C56:F56) -> 0.046800885 | L33: *owners receive £5 for every £100 of capital
B34: Other sales | C34: 421 | D34: 571 | E34: =(C34-D34)/D34 -> -0.26269702
B35: Total | C35: =SUM(C29:C34) -> 16351 | D35: =SUM(D29:D34) -> 17201 | E35: =(C35-D35)/D35 -> -0.049415732 | J35: *market avarages: | K35: https://eqvista.com/debt-to-equity-ratio-by-industry/
B36: Of which DTC | C36: 6343 | D36: 5684 | E36: =(C36-D36)/D36 -> 0.11593948
B40: Revenue structure
B41: Geography | C41: 2024 | D41: 2023 | E41: % of Total
B42: United Kingdom | C42: 16177439 | D42: 16826431 | E42: =C42/$C$45 -> 0.98936854
B43: Rest of Europe | C43: 31684 | D43: 171479 | E43: =C43/$C$45 -> 0.001937708
B44: Rest of the world | C44: 142154 | D44: 203136 | E44: =C44/$C$45 -> 0.0086937552
B45: Total | C45: =SUM(C42:C44) -> 16351277 | D45: =SUM(D42:D44) -> 17201046 | E45: =SUM(E42:E44) -> 1
B47: Shareholders >3%
B48: IPGL & Michael Spencer | C48: 0.27
B49: NigelWray | C49: 0.138
B50: Adrian Bridge | C50: 0.037
B51: Total % of major shareholders | C51: =SUM(C48:C50) -> 0.445
B54: CEO: James Pennefather
B55: CFO: Robert Smith

Sheet Model
A1: Main | B1: *in thousands, GBP
C2: 2021 | D2: 2022 | E2: 2023 | F2: 2024
B3: IS
B4: Revenue | C4: 16639.885 | D4: 17745.581 | E4: 20135.454 | F4: 19844.856
B5: Duty | C5: 0 | D5: 0 | E5: 2214.575 | F5: 2572.153
B6: Retros | C6: 0 | D6: 0 | E6: 719.833 | F6: 921.426
B7: Net Sales | C7: =C4-SUM(C5:C6) -> 16639.885 | D7: =D4-SUM(D5:D6) -> 17745.581 | E7: =E4-SUM(E5:E6) -> 17201.046 | F7: =F4-SUM(F5:F6) -> 16351.277
B8: Cost of Sales | C8: 9592.142 | D8: 9210.423 | E8: =8289.842 -> 8289.842 | F8: 8432.876
B9: Gross profit | C9: =C7-C8 -> 7047.743 | D9: =D7-D8 -> 8535.158 | E9: =E7-E8 -> 8911.204 | F9: =F7-F8 -> 7918.401
B10: SG&A | C10: =5610.351+23.564 -> 5633.915 | D10: =6667.277+57.79 -> 6725.067 | E10: 7394.154 | F10: 7036.706
B11: Gross operating profit | C11: =C9-C10 -> 1413.828 | D11: =D9-D10 -> 1810.091 | E11: =E9-E10 -> 1517.05 | F11: =F9-F10 -> 881.695
B12: Fair value of bio produce | C12: 0 | D12: 0 | E12: 2171.389 | F12: -566.962
B13: Exceptional costs | C13: 287.416 | D13: 109.517 | E13: 1235.478 | F13: 1216.341
B14: Operating profit | C14: =C11+C12-C13 -> 1126.412 | D14: =D11+D12-D13 -> 1700.574 | E14: =E11+E12-E13 -> 2452.961 | F14: =F11+F12-F13 -> -901.608
B15: Finance income | C15: 0.38 | D15: 16.147 | E15: 47.222 | F15: 11.742
B16: Finance costs | C16: 98.723 | D16: 119.041 | E16: 193.057 | F16: 510.513
B17: Other income (expense) | C17: 73.255 | D17: -15.207 | E17: 0 | F17: 0
B18: PreTax | C18: =C14+C15-C16+C17 -> 1101.324 | D18: =D14+D15-D16+D17 -> 1582.473 | E18: =E14+E15-E16 -> 2307.126 | F18: =F14+F15-F16 -> -1400.379
B19: Taxes | C19: -287.485 | D19: 529.441 | E19: 779.773 | F19: =-91.738 -> -91.738
B20: Net income | C20: =C18-C19 -> 1388.809 | D20: =D18-D19 -> 1053.032 | E20: =E18-E19 -> 1527.353 | F20: =F18-F19 -> -1308.641
B22: Shares | C22: =C23*C20*100 -> 131936.85 | D22: =D23*D20*100 -> 100038.04 | E22: =E23*E20*100 -> 145098.54 | F22: =Main!K6 -> 171520
B23: EPS, pence/share | C23: 0.95 | D23: 0.95 | E23: 0.95 | F23: =F20/F22*100 -> -0.762967
B25: Gross margin | C25: =C9/C4 -> 0.42354517 | D25: =D9/D4 -> 0.48097371 | E25: =E9/E4 -> 0.44256285 | F25: =F9/F4 -> 0.39901529
B26: Operating margin | C26: =C14/C4 -> 0.067693497 | D26: =D14/D4 -> 0.095830844 | E26: =E14/E4 -> 0.12182298 | F26: =F14/F4 -> -0.045432832
B27: Profit margin | C27: =C20/C4 -> 0.083462656 | D27: =D20/D4 -> 0.05934052 | E27: =E20/E4 -> 0.075853914 | F27: =F20/F4 -> -0.065943588
B29: Gross profit grwoth y/y | D29: =D4/C4-1 -> 0.066448536 | E29: =E4/D4-1 -> 0.13467426 | F29: =F4/E4-1 -> -0.014432155
B30: Operating profit growth y/y | D30: =D14/C14-1 -> 0.50972646 | E30: =E14/D14-1 -> 0.4424312 | F30: =F14/E14-1 -> -1.367559
B31: Profit growth y/y | D31: =D20/C20-1 -> -0.24177335 | E31: =E20/D20-1 -> 0.45043361 | F31: =F20/E20-1 -> -1.8568032
B35: BS
B36: Cash | C36: 9215 | D36: 5801 | E36: 1004.305 | F36: 981.963
B37: Inventory | C37: 12579 | D37: 15394 | E37: 22581.264 | F37: 26557.669
B38: A/R | C38: 1309 | D38: 2695 | E38: 3593.348 | F38: 4004.523
B39: Current assets | C39: =SUM(C36:C38) -> 23103 | D39: =SUM(D36:D38) -> 23890 | E39: =SUM(E36:E38) -> 27178.917 | F39: =SUM(F36:F38) -> 31544.155
B40: Intangibles | C40: 117 | D40: 79 | E40: 41.803 | F40: 18.303
B41: PP&E | C41: 14578 | D41: 15850 | E41: 23898.348 | F41: 26803.183
B42: Non-current assets | C42: =SUM(C40:C41) -> 14695 | D42: =SUM(D40:D41) -> 15929 | E42: =SUM(E40:E41) -> 23940.151 | F42: =SUM(F40:F41) -> 26821.486
B43: Total assets | C43: =C42+C39 -> 37798 | D43: =D42+D39 -> 39819 | E43: =E42+E39 -> 51119.068 | F43: =F42+F39 -> 58365.641
B45: Short-term debt | C45: 4200 | D45: 4755 | E45: 2240.748 | F45: 9975.683
B46: A/P | C46: 0 | D46: 0 | E46: 5748.571 | F46: 5044.284
B47: Current Lease liabilities | C47: 0 | D47: 0 | E47: 430.655 | F47: 376.45
B48: Current liabilities | C48: =SUM(C45:C47) -> 4200 | D48: =SUM(D45:D47) -> 4755 | E48: =SUM(E45:E47) -> 8419.974 | F48: =SUM(F45:F47) -> 15396.417
B49: Long-term debt | C49: 2482 | D49: 2089 | E49: 0 | F49: 0
B50: A/P | C50: 0 | D50: 0 | E50: 22.63 | F50: 0
B51: Lease liabilities | C51: 0 | D51: 0 | E51: 7457.14 | F51: 9225.616
B52: Deferred tax | C52: 0 | D52: 528 | E52: 893.397 | F52: 1092.013
B53: Total non-current liabilities | C53: =SUM(C49:C52) -> 2482 | D53: =SUM(D49:D52) -> 2617 | E53: =SUM(E49:E52) -> 8373.167 | F53: =SUM(F49:F52) -> 10317.629
B54: Total liabilities | C54: =C53+C48 -> 6682 | D54: =D53+D48 -> 7372 | E54: =E53+E48 -> 16793.141 | F54: =F53+F48 -> 25714.046
B56: Total Equity (A-L) | C56: =C43-C54 -> 31116 | D56: =D43-D54 -> 32447 | E56: =E43-E54 -> 34325.927 | F56: =F43-F54 -> 32651.595
B57: L+E | C57: =C56+C54 -> 37798 | D57: =D56+D54 -> 39819 | E57: =E56+E54 -> 51119.068 | F57: =F56+F54 -> 58365.641
B60: Total assets growth | D60: =D43/C43-1 -> 0.053468437 | E60: =E43/D43-1 -> 0.28378583 | F60: =F43/E43-1 -> 0.14175871
B61: Current assets growth | D61: =D39/C39-1 -> 0.03406484 | E61: =E39/D39-1 -> 0.13766919 | F61: =F39/E39-1 -> 0.16061118
B62: Non-current assets growth | D62: =D42/C42-1 -> 0.083974141 | E62: =E42/D42-1 -> 0.50292868 | F62: =F42/E42-1 -> 0.12035576
B64: Total liabilities change | D64: =D54/C54-1 -> 0.1032625 | E64: =E54/D54-1 -> 1.2779627 | F64: =F54/E54-1 -> 0.53122313
B65: Current liabilities change | D65: =D48/C48-1 -> 0.13214286 | E65: =E48/D48-1 -> 0.77076215 | F65: =F48/E48-1 -> 0.82855873
B66: Long-term liabilities change | D66: =D53/C53-1 -> 0.05439162 | E66: =E53/D53-1 -> 2.1995288 | F66: =F53/E53-1 -> 0.23222539
B68: Equity growth | D68: =D56/C56-1 -> 0.042775421 | E68: =E56/D56-1 -> 0.057907572 | F68: =F56/E56-1 -> -0.048777474
B70: Liquidity current ratio | C70: =C39/C48 -> 5.5007143 | D70: =D39/D48 -> 5.0241851 | E70: =E39/E48 -> 3.2279098 | F70: =F39/F48 -> 2.0487984
B74: CFS
B75: Net income | C75: 1078 | D75: 1053 | E75: 2307 | F75: -1400
B76: Non-cash adjustments | C76: 595 | D76: 1623 | E76: -1608 | F76: 1444
B77: Working capital changes | C77: -234 | D77: -3791 | E77: -2743 | F77: -3838
B78: OCF | C78: 1439 | D78: -1115 | E78: -1911 | F78: -3794
B79: CapEx | C79: -1104 | D79: -2122 | E79: -1817 | F79: -2473
B80: FCF | C80: 335 | D80: -3237 | E80: -3728 | F80: -6267
B81: FCF | C81: 4022 | D81: -193 | E81: -1126 | F81: 6233
B82: Net change in cash | C82: 4355 | D82: -3414 | E82: -4796 | F82: -22
B84: OCF growth y/y | D84: =C78/D78-1 -> -2.290583 | E84: =E78/C78-1 -> -2.3280056 | F84: =F78/E78-1 -> 0.98534799
B85: FCF growth y/y | D85: =C80/D80-1 -> -1.1034909 | E85: =E80/C80-1 -> -12.128358 | F85: =F80/E80-1 -> 0.68106223
B87: *the company is burning cash through aggressive expansion (asset acquisitions, CapEx)
B88: +this is very capital-intensive business
B89: **growth company with poor cash discipline.
B91: The company may increase its use of debt financing to support CapEx and growth
B92: provided that operating cash flow is stabilized and working capital is controlled.

Sheet Definitions
A2: 1 | B2: Duty | C2: expense generally refers to the tax or tariff imposed by a government on goods imported from another country
A3: 2 | B3: Retros | C3: extra income added to an employee's paycheck to compensate the employee for unpaid work performed
A4: 3 | B4: SG&A | C4: Selling, General, and Administrative: all non-production costs required to operate a business. In IS stated as Administrative
A5: 4 | B5: Fair value of bio produce | C5: Agricultural produce, price that would be received to sell the asset in an orderly transaction
A6: 5 | B6: Inventory | C6: Current asset of Biological produce & other inventories
A7: 6 | B7: Cash | C7: Cash and cash equivalents
A8: 7 | B8: A/R | C8: Trade and other receivables
A9: 8 | B9: PP&E | C9: Property, plant, and equipment: tangible, long-term, non-current assets essential for business operations (land, machines)
A10: 9 | B10: Short-term debt | C10: Indicated in BS as Borrowings payable within a year
A11: 10 | B11: A/P | C11: Trade and other payables
A12: 11 | B12: Long-term debt | C12: Indicated in BS as Borrowings with a maturity date longer than one year
A13: 12 | B13: ROA | C13: Return on Assets: ratio measuring how efficiently a company uses its assets to generate earnings
... A17: 16 | B17: CFF | C17: Cash flow from financing activities: measures the net flow of cash between a company and its owners/creditors
